pymela/__init__.py
pymela/commandline.py
pymela/version.py
pymela-0.0.1.dist-info/LICENSE
pymela-0.0.1.dist-info/METADATA
pymela-0.0.1.dist-info/WHEEL
pymela-0.0.1.dist-info/entry_points.txt
pymela-0.0.1.dist-info/top_level.txt
pymela-0.0.1.dist-info/RECORD
